fpodms/__init__.py
fpodms/api.py
fpodms/export.py
fpodms-2.0.0.dist-info/WHEEL
fpodms-2.0.0.dist-info/METADATA
fpodms-2.0.0.dist-info/licenses/LICENSE
fpodms-2.0.0.dist-info/RECORD
