Metadata-Version: 2.1
Name: fpodms
Version: 2.0.0
License: MIT
Author-email: Charlie Bini <5003326+cbini@users.noreply.github.com>
Requires-Python: >=3.9
Requires-Dist: inflection>=0.5.1
Requires-Dist: python-dateutil>=2.8.2
Requires-Dist: requests>=2.28.1
